{
  "updated": "2026-07-02T07:06:11Z",
  "count": 75,
  "stocks": [
    {
      "symbol": "ORCL",
      "name": "Oracle Corporation",
      "date": "2026-07-01",
      "price": 142.5,
      "change": -4.05,
      "change_pct": -2.76,
      "volume": 45829500,
      "avg_volume": 30451015,
      "volume_ratio": 1.505,
      "rsi": 27.4993,
      "sma20": 182.591,
      "sma50": 187.1906,
      "sma150": 176.1574,
      "slope_sma150": -0.3783,
      "ema9": 157.2865,
      "macd": -13.7846,
      "macd_signal": -8.232,
      "macd_histogram": -5.5526,
      "atr": 9.4964,
      "volume_10week_ma": 27327476.0,
      "stage_classification": "Stage 4 (Declining)",
      "confirms_stage2_volume": "N/A",
      "action_signal": "SELL",
      "stage_analysis_summary": "SELL",
      "position": "SELL",
      "signals": [
        "Oversold",
        "Bearish",
        "MACD Bearish"
      ],
      "signal_type": "oversold"
    },
    {
      "symbol": "WMT",
      "name": "Walmart Inc.",
      "date": "2026-07-01",
      "price": 108.82,
      "change": -4.44,
      "change_pct": -3.92,
      "volume": 40341200,
      "avg_volume": 24317160,
      "volume_ratio": 1.659,
      "rsi": 25.9004,
      "sma20": 117.763,
      "sma50": 123.2972,
      "sma150": 121.1947,
      "slope_sma150": 0.1042,
      "ema9": 114.8658,
      "macd": -2.6258,
      "macd_signal": -2.0203,
      "macd_histogram": -0.6055,
      "atr": 2.8029,
      "volume_10week_ma": 22369474.0,
      "stage_classification": "Transitional",
      "confirms_stage2_volume": "N/A",
      "action_signal": "HOLD",
      "stage_analysis_summary": "HOLD",
      "position": "HOLD",
      "signals": [
        "Oversold",
        "Bearish",
        "MACD Bearish"
      ],
      "signal_type": "oversold"
    },
    {
      "symbol": "USO",
      "name": "United States Oil Fund",
      "date": "2026-07-01",
      "price": 103.27,
      "change": -3.17,
      "change_pct": -2.98,
      "volume": 3102900,
      "avg_volume": 5981205,
      "volume_ratio": 0.5188,
      "rsi": 29.1709,
      "sma20": 119.6615,
      "sma50": 131.4802,
      "sma150": 102.9583,
      "slope_sma150": 0.3218,
      "ema9": 109.2326,
      "macd": -7.9914,
      "macd_signal": -6.6655,
      "macd_histogram": -1.3259,
      "atr": 4.8457,
      "volume_10week_ma": 8486176.0,
      "stage_classification": "Stage 2 (Advancing)",
      "confirms_stage2_volume": "N/A",
      "action_signal": "HOLD",
      "stage_analysis_summary": "HOLD",
      "position": "HOLD",
      "signals": [
        "Oversold",
        "Bearish",
        "MACD Bearish"
      ],
      "signal_type": "oversold"
    },
    {
      "symbol": "CVX",
      "name": "Chevron Corporation",
      "date": "2026-07-01",
      "price": 165.69,
      "change": -0.07,
      "change_pct": -0.04,
      "volume": 9165500,
      "avg_volume": 9531600,
      "volume_ratio": 0.9616,
      "rsi": 28.0434,
      "sma20": 179.082,
      "sma50": 183.6736,
      "sma150": 176.3473,
      "slope_sma150": 0.1945,
      "ema9": 171.0971,
      "macd": -5.24,
      "macd_signal": -3.8101,
      "macd_histogram": -1.4298,
      "atr": 4.0743,
      "volume_10week_ma": 9818970.0,
      "stage_classification": "Transitional",
      "confirms_stage2_volume": "N/A",
      "action_signal": "HOLD",
      "stage_analysis_summary": "HOLD",
      "position": "HOLD",
      "signals": [
        "Oversold",
        "Bearish",
        "MACD Bearish"
      ],
      "signal_type": "oversold"
    },
    {
      "symbol": "OXY",
      "name": "Occidental Petroleum Corporatio",
      "date": "2026-07-01",
      "price": 47.94,
      "change": -0.63,
      "change_pct": -1.3,
      "volume": 8488000,
      "avg_volume": 9797870,
      "volume_ratio": 0.8663,
      "rsi": 25.7461,
      "sma20": 53.608,
      "sma50": 55.9484,
      "sma150": 51.0286,
      "slope_sma150": 0.086,
      "ema9": 50.3864,
      "macd": -2.2365,
      "macd_signal": -1.6543,
      "macd_histogram": -0.5822,
      "atr": 1.6529,
      "volume_10week_ma": 11104996.0,
      "stage_classification": "Transitional",
      "confirms_stage2_volume": "N/A",
      "action_signal": "HOLD",
      "stage_analysis_summary": "HOLD",
      "position": "HOLD",
      "signals": [
        "Oversold",
        "Bearish",
        "MACD Bearish"
      ],
      "signal_type": "oversold"
    },
    {
      "symbol": "T",
      "name": "AT&T Inc.",
      "date": "2026-07-01",
      "price": 20.48,
      "change": -0.22,
      "change_pct": -1.06,
      "volume": 137645600,
      "avg_volume": 62504150,
      "volume_ratio": 2.2022,
      "rsi": 27.2532,
      "sma20": 22.5195,
      "sma50": 24.1974,
      "sma150": 25.3421,
      "slope_sma150": -0.0141,
      "ema9": 21.7975,
      "macd": -0.8512,
      "macd_signal": -0.7192,
      "macd_histogram": -0.1321,
      "atr": 0.6871,
      "volume_10week_ma": 49339358.0,
      "stage_classification": "Stage 4 (Declining)",
      "confirms_stage2_volume": "N/A",
      "action_signal": "SELL",
      "stage_analysis_summary": "SELL",
      "position": "SELL",
      "signals": [
        "Oversold",
        "Bearish",
        "MACD Bearish",
        "High Volume"
      ],
      "signal_type": "oversold"
    },
    {
      "symbol": "META",
      "name": "Meta Platforms, Inc.",
      "date": "2026-07-01",
      "price": 612.91,
      "change": 49.62,
      "change_pct": 8.81,
      "volume": 45473000,
      "avg_volume": 18403645,
      "volume_ratio": 2.4709,
      "rsi": 58.5117,
      "sma20": 578.484,
      "sma50": 606.5127,
      "sma150": 629.8036,
      "slope_sma150": -0.3894,
      "ema9": 573.1407,
      "macd": -9.7691,
      "macd_signal": -12.9241,
      "macd_histogram": 3.155,
      "atr": 21.8455,
      "volume_10week_ma": 17621662.0,
      "stage_classification": "Stage 4 (Declining)",
      "confirms_stage2_volume": "N/A",
      "action_signal": "SELL",
      "stage_analysis_summary": "SELL",
      "position": "SELL",
      "signals": [
        "Momentum",
        "MACD Bullish",
        "High Volume",
        "Breakout"
      ],
      "signal_type": "bullish"
    },
    {
      "symbol": "TSLA",
      "name": "Tesla, Inc.",
      "date": "2026-07-01",
      "price": 425.3,
      "change": 4.7,
      "change_pct": 1.12,
      "volume": 39967100,
      "avg_volume": 47868200,
      "volume_ratio": 0.8349,
      "rsi": 58.2333,
      "sma20": 400.6695,
      "sma50": 406.2794,
      "sma150": 413.7346,
      "slope_sma150": -0.2101,
      "ema9": 403.9576,
      "macd": -0.9507,
      "macd_signal": -3.6991,
      "macd_histogram": 2.7484,
      "atr": 17.3214,
      "volume_10week_ma": 51554116.0,
      "stage_classification": "Transitional",
      "confirms_stage2_volume": "N/A",
      "action_signal": "HOLD",
      "stage_analysis_summary": "HOLD",
      "position": "HOLD",
      "signals": [
        "Momentum",
        "MACD Bullish"
      ],
      "signal_type": "bullish"
    },
    {
      "symbol": "JPM",
      "name": "JP Morgan Chase & Co.",
      "date": "2026-07-01",
      "price": 334.07,
      "change": 6.74,
      "change_pct": 2.06,
      "volume": 15201800,
      "avg_volume": 9901695,
      "volume_ratio": 1.5353,
      "rsi": 63.3483,
      "sma20": 322.726,
      "sma50": 312.182,
      "sma150": 307.4784,
      "slope_sma150": 0.1181,
      "ema9": 329.6154,
      "macd": 6.8508,
      "macd_signal": 6.5834,
      "macd_histogram": 0.2674,
      "atr": 8.0421,
      "volume_10week_ma": 8984978.0,
      "stage_classification": "Stage 2 (Advancing)",
      "confirms_stage2_volume": "Strong Volume Confirmation",
      "action_signal": "BUY",
      "stage_analysis_summary": "BUY",
      "position": "BUY",
      "signals": [
        "Momentum",
        "Bullish",
        "MACD Bullish",
        "Breakout"
      ],
      "signal_type": "bullish"
    },
    {
      "symbol": "BAC",
      "name": "Bank of America Corporation",
      "date": "2026-07-01",
      "price": 58.36,
      "change": 1.38,
      "change_pct": 2.42,
      "volume": 35268600,
      "avg_volume": 38652800,
      "volume_ratio": 0.9124,
      "rsi": 69.3469,
      "sma20": 56.068,
      "sma50": 53.3728,
      "sma150": 52.3994,
      "slope_sma150": 0.0276,
      "ema9": 57.4201,
      "macd": 1.5085,
      "macd_signal": 1.4544,
      "macd_histogram": 0.0541,
      "atr": 1.2179,
      "volume_10week_ma": 35933106.0,
      "stage_classification": "Stage 2 (Advancing)",
      "confirms_stage2_volume": "N/A",
      "action_signal": "HOLD",
      "stage_analysis_summary": "HOLD",
      "position": "HOLD",
      "signals": [
        "Momentum",
        "Bullish",
        "MACD Bullish"
      ],
      "signal_type": "bullish"
    },
    {
      "symbol": "MA",
      "name": "Mastercard Incorporated",
      "date": "2026-07-01",
      "price": 522.44,
      "change": 8.84,
      "change_pct": 1.72,
      "volume": 4412800,
      "avg_volume": 4368130,
      "volume_ratio": 1.0102,
      "rsi": 65.4422,
      "sma20": 493.2905,
      "sma50": 496.8892,
      "sma150": 519.95,
      "slope_sma150": -0.3632,
      "ema9": 503.7927,
      "macd": 4.0899,
      "macd_signal": 0.3547,
      "macd_histogram": 3.7352,
      "atr": 11.2521,
      "volume_10week_ma": 3973828.0,
      "stage_classification": "Transitional",
      "confirms_stage2_volume": "N/A",
      "action_signal": "HOLD",
      "stage_analysis_summary": "HOLD",
      "position": "HOLD",
      "signals": [
        "Momentum",
        "MACD Bullish"
      ],
      "signal_type": "bullish"
    },
    {
      "symbol": "HD",
      "name": "Home Depot, Inc. (The)",
      "date": "2026-07-01",
      "price": 350.84,
      "change": -1.84,
      "change_pct": -0.52,
      "volume": 4038600,
      "avg_volume": 5352195,
      "volume_ratio": 0.7546,
      "rsi": 66.6032,
      "sma20": 330.326,
      "sma50": 321.5536,
      "sma150": 342.3347,
      "slope_sma150": -0.1929,
      "ema9": 343.4804,
      "macd": 8.9757,
      "macd_signal": 6.3036,
      "macd_histogram": 2.6721,
      "atr": 8.7314,
      "volume_10week_ma": 5124830.0,
      "stage_classification": "Transitional",
      "confirms_stage2_volume": "N/A",
      "action_signal": "HOLD",
      "stage_analysis_summary": "HOLD",
      "position": "HOLD",
      "signals": [
        "Momentum",
        "Bullish",
        "MACD Bullish"
      ],
      "signal_type": "bullish"
    },
    {
      "symbol": "LIN",
      "name": "Linde plc",
      "date": "2026-07-01",
      "price": 533.55,
      "change": 14.61,
      "change_pct": 2.82,
      "volume": 3085900,
      "avg_volume": 2644235,
      "volume_ratio": 1.167,
      "rsi": 63.1483,
      "sma20": 515.24,
      "sma50": 507.8641,
      "sma150": 474.2868,
      "slope_sma150": 0.6477,
      "ema9": 519.7468,
      "macd": 4.4729,
      "macd_signal": 3.6452,
      "macd_histogram": 0.8277,
      "atr": 11.2471,
      "volume_10week_ma": 2316934.0,
      "stage_classification": "Stage 2 (Advancing)",
      "confirms_stage2_volume": "Strong Volume Confirmation",
      "action_signal": "BUY",
      "stage_analysis_summary": "BUY",
      "position": "BUY",
      "signals": [
        "Momentum",
        "Bullish",
        "MACD Bullish"
      ],
      "signal_type": "bullish"
    },
    {
      "symbol": "APD",
      "name": "Air Products and Chemicals, Inc",
      "date": "2026-07-01",
      "price": 306.4,
      "change": 15.03,
      "change_pct": 5.16,
      "volume": 2692300,
      "avg_volume": 1546625,
      "volume_ratio": 1.7408,
      "rsi": 68.2612,
      "sma20": 280.4435,
      "sma50": 288.2526,
      "sma150": 274.5455,
      "slope_sma150": 0.218,
      "ema9": 285.0041,
      "macd": 0.4616,
      "macd_signal": -2.1051,
      "macd_histogram": 2.5667,
      "atr": 9.3296,
      "volume_10week_ma": 1308334.0,
      "stage_classification": "Stage 2 (Advancing)",
      "confirms_stage2_volume": "Strong Volume Confirmation",
      "action_signal": "BUY",
      "stage_analysis_summary": "BUY",
      "position": "BUY",
      "signals": [
        "Momentum",
        "MACD Bullish",
        "Breakout"
      ],
      "signal_type": "bullish"
    },
    {
      "symbol": "SHW",
      "name": "Sherwin-Williams Company (The)",
      "date": "2026-07-01",
      "price": 346.05,
      "change": 1.73,
      "change_pct": 0.5,
      "volume": 2396300,
      "avg_volume": 2895160,
      "volume_ratio": 0.8277,
      "rsi": 69.3203,
      "sma20": 320.905,
      "sma50": 316.6335,
      "sma150": 330.5733,
      "slope_sma150": -0.1048,
      "ema9": 336.2344,
      "macd": 9.0011,
      "macd_signal": 5.4684,
      "macd_histogram": 3.5327,
      "atr": 9.3457,
      "volume_10week_ma": 2413998.0,
      "stage_classification": "Transitional",
      "confirms_stage2_volume": "N/A",
      "action_signal": "HOLD",
      "stage_analysis_summary": "HOLD",
      "position": "HOLD",
      "signals": [
        "Momentum",
        "Bullish",
        "MACD Bullish"
      ],
      "signal_type": "bullish"
    },
    {
      "symbol": "ECL",
      "name": "Ecolab Inc.",
      "date": "2026-07-01",
      "price": 278.37,
      "change": -0.24,
      "change_pct": -0.09,
      "volume": 1231100,
      "avg_volume": 1934065,
      "volume_ratio": 0.6365,
      "rsi": 62.5655,
      "sma20": 268.2414,
      "sma50": 261.1869,
      "sma150": 270.2364,
      "slope_sma150": 0.0668,
      "ema9": 276.0388,
      "macd": 5.8231,
      "macd_signal": 4.64,
      "macd_histogram": 1.1831,
      "atr": 6.8019,
      "volume_10week_ma": 1738314.0,
      "stage_classification": "Stage 2 (Advancing)",
      "confirms_stage2_volume": "N/A",
      "action_signal": "HOLD",
      "stage_analysis_summary": "HOLD",
      "position": "HOLD",
      "signals": [
        "Momentum",
        "Bullish",
        "MACD Bullish"
      ],
      "signal_type": "bullish"
    },
    {
      "symbol": "CL",
      "name": "Colgate-Palmolive Company",
      "date": "2026-07-01",
      "price": 92.76,
      "change": 1.08,
      "change_pct": 1.18,
      "volume": 4040600,
      "avg_volume": 5730835,
      "volume_ratio": 0.7051,
      "rsi": 60.3681,
      "sma20": 89.723,
      "sma50": 88.374,
      "sma150": 86.221,
      "slope_sma150": 0.085,
      "ema9": 91.4949,
      "macd": 1.0783,
      "macd_signal": 0.856,
      "macd_histogram": 0.2223,
      "atr": 1.7657,
      "volume_10week_ma": 5452114.0,
      "stage_classification": "Stage 2 (Advancing)",
      "confirms_stage2_volume": "N/A",
      "action_signal": "HOLD",
      "stage_analysis_summary": "HOLD",
      "position": "HOLD",
      "signals": [
        "Momentum",
        "Bullish",
        "MACD Bullish"
      ],
      "signal_type": "bullish"
    },
    {
      "symbol": "GIS",
      "name": "General Mills, Inc.",
      "date": "2026-07-01",
      "price": 37.77,
      "change": 2.97,
      "change_pct": 8.53,
      "volume": 27486700,
      "avg_volume": 10831345,
      "volume_ratio": 2.5377,
      "rsi": 67.7178,
      "sma20": 34.2455,
      "sma50": 34.2174,
      "sma150": 39.7143,
      "slope_sma150": -0.0759,
      "ema9": 35.507,
      "macd": 0.5937,
      "macd_signal": 0.2184,
      "macd_histogram": 0.3752,
      "atr": 1.0786,
      "volume_10week_ma": 10269220.0,
      "stage_classification": "Stage 4 (Declining)",
      "confirms_stage2_volume": "N/A",
      "action_signal": "SELL",
      "stage_analysis_summary": "SELL",
      "position": "SELL",
      "signals": [
        "Momentum",
        "Bullish",
        "MACD Bullish",
        "High Volume",
        "Breakout"
      ],
      "signal_type": "bullish"
    },
    {
      "symbol": "KHC",
      "name": "The Kraft Heinz Company",
      "date": "2026-07-01",
      "price": 25.01,
      "change": 1.39,
      "change_pct": 5.88,
      "volume": 18339500,
      "avg_volume": 14340155,
      "volume_ratio": 1.2789,
      "rsi": 63.2643,
      "sma20": 23.3842,
      "sma50": 22.9585,
      "sma150": 22.9822,
      "slope_sma150": -0.0006,
      "ema9": 23.7679,
      "macd": 0.2635,
      "macd_signal": 0.1473,
      "macd_histogram": 0.1162,
      "atr": 0.6597,
      "volume_10week_ma": 14367674.0,
      "stage_classification": "Transitional",
      "confirms_stage2_volume": "N/A",
      "action_signal": "HOLD",
      "stage_analysis_summary": "HOLD",
      "position": "HOLD",
      "signals": [
        "Momentum",
        "Bullish",
        "MACD Bullish"
      ],
      "signal_type": "bullish"
    },
    {
      "symbol": "CLX",
      "name": "Clorox Company (The)",
      "date": "2026-07-01",
      "price": 96.42,
      "change": 0.98,
      "change_pct": 1.03,
      "volume": 1827600,
      "avg_volume": 2577765,
      "volume_ratio": 0.709,
      "rsi": 52.8691,
      "sma20": 95.251,
      "sma50": 93.8976,
      "sma150": 102.9273,
      "slope_sma150": -0.06,
      "ema9": 95.7686,
      "macd": 0.444,
      "macd_signal": 0.2827,
      "macd_histogram": 0.1613,
      "atr": 3.0629,
      "volume_10week_ma": 3051984.0,
      "stage_classification": "Stage 4 (Declining)",
      "confirms_stage2_volume": "N/A",
      "action_signal": "SELL",
      "stage_analysis_summary": "SELL",
      "position": "SELL",
      "signals": [
        "Momentum",
        "Bullish",
        "MACD Bullish"
      ],
      "signal_type": "bullish"
    },
    {
      "symbol": "DBA",
      "name": "Invesco DB Agriculture Fund",
      "date": "2026-07-01",
      "price": 26.86,
      "change": 0.19,
      "change_pct": 0.71,
      "volume": 517900,
      "avg_volume": 1348200,
      "volume_ratio": 0.3841,
      "rsi": 50.1982,
      "sma20": 26.5755,
      "sma50": 27.3266,
      "sma150": 26.4824,
      "slope_sma150": 0.0078,
      "ema9": 26.6986,
      "macd": -0.1416,
      "macd_signal": -0.2067,
      "macd_histogram": 0.0651,
      "atr": 0.2293,
      "volume_10week_ma": 1491254.0,
      "stage_classification": "Stage 2 (Advancing)",
      "confirms_stage2_volume": "N/A",
      "action_signal": "HOLD",
      "stage_analysis_summary": "HOLD",
      "position": "HOLD",
      "signals": [
        "Momentum",
        "MACD Bullish"
      ],
      "signal_type": "bullish"
    },
    {
      "symbol": "KO",
      "name": "Coca-Cola Company (The)",
      "date": "2026-07-01",
      "price": 81.29,
      "change": 0.02,
      "change_pct": 0.02,
      "volume": 21716500,
      "avg_volume": 20696665,
      "volume_ratio": 1.0493,
      "rsi": 54.7812,
      "sma20": 80.4877,
      "sma50": 79.3125,
      "sma150": 75.4742,
      "slope_sma150": 0.0779,
      "ema9": 81.1856,
      "macd": 0.6277,
      "macd_signal": 0.5682,
      "macd_histogram": 0.0595,
      "atr": 1.4638,
      "volume_10week_ma": 17365034.0,
      "stage_classification": "Stage 2 (Advancing)",
      "confirms_stage2_volume": "Strong Volume Confirmation",
      "action_signal": "BUY",
      "stage_analysis_summary": "BUY",
      "position": "BUY",
      "signals": [
        "Momentum",
        "Bullish",
        "MACD Bullish"
      ],
      "signal_type": "bullish"
    },
    {
      "symbol": "MO",
      "name": "Altria Group, Inc.",
      "date": "2026-07-01",
      "price": 71.54,
      "change": -0.41,
      "change_pct": -0.57,
      "volume": 6423200,
      "avg_volume": 8716080,
      "volume_ratio": 0.7369,
      "rsi": 52.5373,
      "sma20": 70.9783,
      "sma50": 70.0623,
      "sma150": 64.0358,
      "slope_sma150": 0.1017,
      "ema9": 71.9665,
      "macd": 0.7529,
      "macd_signal": 0.6069,
      "macd_histogram": 0.146,
      "atr": 1.593,
      "volume_10week_ma": 8998210.0,
      "stage_classification": "Stage 2 (Advancing)",
      "confirms_stage2_volume": "N/A",
      "action_signal": "HOLD",
      "stage_analysis_summary": "HOLD",
      "position": "HOLD",
      "signals": [
        "Momentum",
        "Bullish",
        "MACD Bullish"
      ],
      "signal_type": "bullish"
    },
    {
      "symbol": "JNJ",
      "name": "Johnson & Johnson",
      "date": "2026-07-01",
      "price": 253.98,
      "change": 0.01,
      "change_pct": 0.0,
      "volume": 6512000,
      "avg_volume": 9029095,
      "volume_ratio": 0.7212,
      "rsi": 67.6821,
      "sma20": 239.0915,
      "sma50": 231.3741,
      "sma150": 227.0383,
      "slope_sma150": 0.3323,
      "ema9": 247.869,
      "macd": 6.1827,
      "macd_signal": 4.0371,
      "macd_histogram": 2.1457,
      "atr": 5.8214,
      "volume_10week_ma": 8272220.0,
      "stage_classification": "Stage 2 (Advancing)",
      "confirms_stage2_volume": "N/A",
      "action_signal": "HOLD",
      "stage_analysis_summary": "HOLD",
      "position": "HOLD",
      "signals": [
        "Momentum",
        "Bullish",
        "MACD Bullish"
      ],
      "signal_type": "bullish"
    },
    {
      "symbol": "MRK",
      "name": "Merck & Company, Inc.",
      "date": "2026-07-01",
      "price": 125.37,
      "change": -3.13,
      "change_pct": -2.44,
      "volume": 10757000,
      "avg_volume": 12834830,
      "volume_ratio": 0.8381,
      "rsi": 60.9851,
      "sma20": 119.969,
      "sma50": 115.8474,
      "sma150": 112.635,
      "slope_sma150": 0.2171,
      "ema9": 124.1545,
      "macd": 2.9602,
      "macd_signal": 1.9201,
      "macd_histogram": 1.0401,
      "atr": 3.3902,
      "volume_10week_ma": 10655638.0,
      "stage_classification": "Stage 2 (Advancing)",
      "confirms_stage2_volume": "Strong Volume Confirmation",
      "action_signal": "BUY",
      "stage_analysis_summary": "BUY",
      "position": "BUY",
      "signals": [
        "Momentum",
        "Bullish",
        "MACD Bullish"
      ],
      "signal_type": "bullish"
    },
    {
      "symbol": "LMT",
      "name": "Lockheed Martin Corporation",
      "date": "2026-07-01",
      "price": 521.82,
      "change": 12.36,
      "change_pct": 2.43,
      "volume": 1277500,
      "avg_volume": 1363965,
      "volume_ratio": 0.9366,
      "rsi": 51.4507,
      "sma20": 518.1665,
      "sma50": 518.9981,
      "sma150": 554.1497,
      "slope_sma150": 0.3664,
      "ema9": 511.3132,
      "macd": -5.6284,
      "macd_signal": -5.7832,
      "macd_histogram": 0.1548,
      "atr": 15.53,
      "volume_10week_ma": 1469264.0,
      "stage_classification": "Transitional",
      "confirms_stage2_volume": "N/A",
      "action_signal": "HOLD",
      "stage_analysis_summary": "HOLD",
      "position": "HOLD",
      "signals": [
        "Momentum",
        "MACD Bullish"
      ],
      "signal_type": "bullish"
    },
    {
      "symbol": "RTX",
      "name": "RTX Corporation",
      "date": "2026-07-01",
      "price": 191.78,
      "change": 2.05,
      "change_pct": 1.08,
      "volume": 3775200,
      "avg_volume": 5463335,
      "volume_ratio": 0.691,
      "rsi": 61.2769,
      "sma20": 184.1805,
      "sma50": 179.1866,
      "sma150": 187.779,
      "slope_sma150": 0.0673,
      "ema9": 187.6988,
      "macd": 2.6778,
      "macd_signal": 2.0025,
      "macd_histogram": 0.6753,
      "atr": 4.6764,
      "volume_10week_ma": 5819036.0,
      "stage_classification": "Stage 2 (Advancing)",
      "confirms_stage2_volume": "N/A",
      "action_signal": "HOLD",
      "stage_analysis_summary": "HOLD",
      "position": "HOLD",
      "signals": [
        "Momentum",
        "Bullish",
        "MACD Bullish"
      ],
      "signal_type": "bullish"
    },
    {
      "symbol": "GD",
      "name": "General Dynamics Corporation",
      "date": "2026-07-01",
      "price": 362.86,
      "change": 8.62,
      "change_pct": 2.43,
      "volume": 1285300,
      "avg_volume": 1427380,
      "volume_ratio": 0.9005,
      "rsi": 61.2985,
      "sma20": 350.1375,
      "sma50": 342.946,
      "sma150": 345.7148,
      "slope_sma150": 0.0562,
      "ema9": 352.3116,
      "macd": 2.5708,
      "macd_signal": 2.2511,
      "macd_histogram": 0.3197,
      "atr": 9.265,
      "volume_10week_ma": 1381310.0,
      "stage_classification": "Stage 2 (Advancing)",
      "confirms_stage2_volume": "N/A",
      "action_signal": "HOLD",
      "stage_analysis_summary": "HOLD",
      "position": "HOLD",
      "signals": [
        "Momentum",
        "Bullish",
        "MACD Bullish"
      ],
      "signal_type": "bullish"
    },
    {
      "symbol": "AMD",
      "name": "Advanced Micro Devices, Inc.",
      "date": "2026-07-01",
      "price": 540.88,
      "change": -40.03,
      "change_pct": -6.89,
      "volume": 28186200,
      "avg_volume": 31943815,
      "volume_ratio": 0.8824,
      "rsi": 56.478,
      "sma20": 518.0705,
      "sma50": 455.7142,
      "sma150": 297.0338,
      "slope_sma150": 1.8306,
      "ema9": 537.4779,
      "macd": 26.3429,
      "macd_signal": 27.5845,
      "macd_histogram": -1.2415,
      "atr": 36.7064,
      "volume_10week_ma": 37836476.0,
      "stage_classification": "Stage 2 (Advancing)",
      "confirms_stage2_volume": "N/A",
      "action_signal": "HOLD",
      "stage_analysis_summary": "HOLD",
      "position": "HOLD",
      "signals": [
        "Momentum",
        "Bullish",
        "MACD Bearish"
      ],
      "signal_type": "bullish"
    },
    {
      "symbol": "AMZN",
      "name": "Amazon.com, Inc.",
      "date": "2026-07-01",
      "price": 241.7,
      "change": 3.36,
      "change_pct": 1.41,
      "volume": 53390300,
      "avg_volume": 63011075,
      "volume_ratio": 0.8473,
      "rsi": 47.8494,
      "sma20": 240.6135,
      "sma50": 255.5616,
      "sma150": 234.646,
      "slope_sma150": 0.0293,
      "ema9": 238.0395,
      "macd": -5.0608,
      "macd_signal": -5.5309,
      "macd_histogram": 0.4701,
      "atr": 8.8664,
      "volume_10week_ma": 51796318.0,
      "stage_classification": "Stage 2 (Advancing)",
      "confirms_stage2_volume": "Strong Volume Confirmation",
      "action_signal": "BUY",
      "stage_analysis_summary": "BUY",
      "position": "BUY",
      "signals": [
        "MACD Bullish"
      ],
      "signal_type": "bullish"
    },
    {
      "symbol": "INTC",
      "name": "Intel Corporation",
      "date": "2026-07-01",
      "price": 127.02,
      "change": -12.61,
      "change_pct": -9.03,
      "volume": 112619200,
      "avg_volume": 131198860,
      "volume_ratio": 0.8584,
      "rsi": 53.4598,
      "sma20": 122.7425,
      "sma50": 112.2994,
      "sma150": 67.9319,
      "slope_sma150": 0.568,
      "ema9": 130.3744,
      "macd": 6.7263,
      "macd_signal": 6.8493,
      "macd_histogram": -0.123,
      "atr": 11.1557,
      "volume_10week_ma": 141069952.0,
      "stage_classification": "Stage 2 (Advancing)",
      "confirms_stage2_volume": "N/A",
      "action_signal": "HOLD",
      "stage_analysis_summary": "HOLD",
      "position": "HOLD",
      "signals": [
        "Momentum",
        "Bullish",
        "MACD Bearish"
      ],
      "signal_type": "bullish"
    },
    {
      "symbol": "PYPL",
      "name": "PayPal Holdings, Inc.",
      "date": "2026-07-01",
      "price": 44.07,
      "change": 0.89,
      "change_pct": 2.06,
      "volume": 22964200,
      "avg_volume": 17372145,
      "volume_ratio": 1.3219,
      "rsi": 53.9397,
      "sma20": 42.4125,
      "sma50": 44.8961,
      "sma150": 49.0458,
      "slope_sma150": -0.1521,
      "ema9": 43.2614,
      "macd": -0.1737,
      "macd_signal": -0.5437,
      "macd_histogram": 0.37,
      "atr": 1.4436,
      "volume_10week_ma": 15852016.0,
      "stage_classification": "Stage 4 (Declining)",
      "confirms_stage2_volume": "N/A",
      "action_signal": "SELL",
      "stage_analysis_summary": "SELL",
      "position": "SELL",
      "signals": [
        "Momentum",
        "MACD Bullish"
      ],
      "signal_type": "bullish"
    },
    {
      "symbol": "UNH",
      "name": "UnitedHealth Group Incorporated",
      "date": "2026-07-01",
      "price": 426.54,
      "change": 10.91,
      "change_pct": 2.62,
      "volume": 4980400,
      "avg_volume": 7237610,
      "volume_ratio": 0.6881,
      "rsi": 66.2937,
      "sma20": 407.1054,
      "sma50": 387.2232,
      "sma150": 331.3442,
      "slope_sma150": 0.5479,
      "ema9": 415.9156,
      "macd": 11.0983,
      "macd_signal": 10.687,
      "macd_histogram": 0.4113,
      "atr": 10.018,
      "volume_10week_ma": 7511046.0,
      "stage_classification": "Stage 2 (Advancing)",
      "confirms_stage2_volume": "N/A",
      "action_signal": "HOLD",
      "stage_analysis_summary": "HOLD",
      "position": "HOLD",
      "signals": [
        "Momentum",
        "Bullish",
        "MACD Bullish"
      ],
      "signal_type": "bullish"
    },
    {
      "symbol": "IRDM",
      "name": "Iridium Communications Inc",
      "date": "2026-07-01",
      "price": 55.72,
      "change": 0.87,
      "change_pct": 1.59,
      "volume": 3356700,
      "avg_volume": 3555390,
      "volume_ratio": 0.9441,
      "rsi": 67.1751,
      "sma20": 47.0662,
      "sma50": 44.6637,
      "sma150": 30.0382,
      "slope_sma150": 0.2022,
      "ema9": 49.3886,
      "macd": 1.7275,
      "macd_signal": 0.7873,
      "macd_histogram": 0.9402,
      "atr": 3.798,
      "volume_10week_ma": 2860582.0,
      "stage_classification": "Stage 2 (Advancing)",
      "confirms_stage2_volume": "Strong Volume Confirmation",
      "action_signal": "BUY",
      "stage_analysis_summary": "BUY",
      "position": "BUY",
      "signals": [
        "Momentum",
        "Bullish",
        "MACD Bullish"
      ],
      "signal_type": "bullish"
    },
    {
      "symbol": "AAPL",
      "name": "Apple Inc.",
      "date": "2026-07-01",
      "price": 294.38,
      "change": 5.02,
      "change_pct": 1.73,
      "volume": 50109500,
      "avg_volume": 67616010,
      "volume_ratio": 0.7411,
      "rsi": 50.9861,
      "sma20": 294.884,
      "sma50": 292.6025,
      "sma150": 273.6749,
      "slope_sma150": 0.1696,
      "ema9": 289.906,
      "macd": -2.248,
      "macd_signal": -0.9912,
      "macd_histogram": -1.2568,
      "atr": 8.3464,
      "volume_10week_ma": 56019270.0,
      "stage_classification": "Stage 2 (Advancing)",
      "confirms_stage2_volume": "N/A",
      "action_signal": "HOLD",
      "stage_analysis_summary": "HOLD",
      "position": "HOLD",
      "signals": [
        "Momentum",
        "MACD Bearish"
      ],
      "signal_type": "neutral"
    },
    {
      "symbol": "GOOGL",
      "name": "Alphabet Inc.",
      "date": "2026-07-01",
      "price": 361.21,
      "change": 3.84,
      "change_pct": 1.07,
      "volume": 26687500,
      "avg_volume": 40977200,
      "volume_ratio": 0.6513,
      "rsi": 50.3685,
      "sma20": 358.4652,
      "sma50": 370.2698,
      "sma150": 333.0627,
      "slope_sma150": 0.5076,
      "ema9": 354.3503,
      "macd": -5.0162,
      "macd_signal": -4.9082,
      "macd_histogram": -0.108,
      "atr": 12.3793,
      "volume_10week_ma": 33481854.0,
      "stage_classification": "Stage 2 (Advancing)",
      "confirms_stage2_volume": "N/A",
      "action_signal": "HOLD",
      "stage_analysis_summary": "HOLD",
      "position": "HOLD",
      "signals": [
        "Momentum",
        "MACD Bearish"
      ],
      "signal_type": "neutral"
    },
    {
      "symbol": "CRM",
      "name": "Salesforce, Inc.",
      "date": "2026-07-01",
      "price": 163.23,
      "change": 6.57,
      "change_pct": 4.19,
      "volume": 14153200,
      "avg_volume": 17493080,
      "volume_ratio": 0.8091,
      "rsi": 47.2226,
      "sma20": 164.9552,
      "sma50": 174.4755,
      "sma150": 201.0664,
      "slope_sma150": -0.5204,
      "ema9": 158.4521,
      "macd": -6.0978,
      "macd_signal": -6.4029,
      "macd_histogram": 0.305,
      "atr": 6.1729,
      "volume_10week_ma": 15511320.0,
      "stage_classification": "Stage 4 (Declining)",
      "confirms_stage2_volume": "N/A",
      "action_signal": "SELL",
      "stage_analysis_summary": "SELL",
      "position": "SELL",
      "signals": [
        "Bearish",
        "MACD Bullish"
      ],
      "signal_type": "neutral"
    },
    {
      "symbol": "HII",
      "name": "Huntington Ingalls Industries, ",
      "date": "2026-07-01",
      "price": 278.97,
      "change": -0.92,
      "change_pct": -0.33,
      "volume": 395400,
      "avg_volume": 531540,
      "volume_ratio": 0.7439,
      "rsi": 35.0377,
      "sma20": 288.588,
      "sma50": 315.4842,
      "sma150": 362.1797,
      "slope_sma150": -0.1246,
      "ema9": 282.25,
      "macd": -10.9897,
      "macd_signal": -11.7854,
      "macd_histogram": 0.7957,
      "atr": 7.9679,
      "volume_10week_ma": 559896.0,
      "stage_classification": "Stage 4 (Declining)",
      "confirms_stage2_volume": "N/A",
      "action_signal": "SELL",
      "stage_analysis_summary": "SELL",
      "position": "SELL",
      "signals": [
        "Bearish",
        "MACD Bullish"
      ],
      "signal_type": "neutral"
    },
    {
      "symbol": "MS",
      "name": "Morgan Stanley",
      "date": "2026-07-01",
      "price": 211.86,
      "change": 2.82,
      "change_pct": 1.35,
      "volume": 4683100,
      "avg_volume": 6514675,
      "volume_ratio": 0.7189,
      "rsi": 50.1509,
      "sma20": 216.09,
      "sma50": 203.2126,
      "sma150": 183.1127,
      "slope_sma150": 0.3629,
      "ema9": 215.0219,
      "macd": 3.2259,
      "macd_signal": 5.3413,
      "macd_histogram": -2.1153,
      "atr": 6.2164,
      "volume_10week_ma": 5783672.0,
      "stage_classification": "Stage 2 (Advancing)",
      "confirms_stage2_volume": "N/A",
      "action_signal": "HOLD",
      "stage_analysis_summary": "HOLD",
      "position": "HOLD",
      "signals": [
        "Momentum",
        "MACD Bearish"
      ],
      "signal_type": "neutral"
    },
    {
      "symbol": "QTUM",
      "name": "Defiance Quantum ETF",
      "date": "2026-07-01",
      "price": 160.36,
      "change": -5.02,
      "change_pct": -3.04,
      "volume": 656800,
      "avg_volume": 920190,
      "volume_ratio": 0.7138,
      "rsi": 52.4217,
      "sma20": 161.1384,
      "sma50": 150.5392,
      "sma150": 125.8421,
      "slope_sma150": 0.35,
      "ema9": 161.4946,
      "macd": 3.0602,
      "macd_signal": 4.1251,
      "macd_histogram": -1.0649,
      "atr": 5.9628,
      "volume_10week_ma": 801156.0,
      "stage_classification": "Stage 2 (Advancing)",
      "confirms_stage2_volume": "N/A",
      "action_signal": "HOLD",
      "stage_analysis_summary": "HOLD",
      "position": "HOLD",
      "signals": [
        "Momentum",
        "MACD Bearish"
      ],
      "signal_type": "neutral"
    },
    {
      "symbol": "MSFT",
      "name": "Microsoft Corporation",
      "date": "2026-07-01",
      "price": 384.28,
      "change": 11.26,
      "change_pct": 3.02,
      "volume": 47966000,
      "avg_volume": 48209270,
      "volume_ratio": 0.995,
      "rsi": 46.9883,
      "sma20": 388.798,
      "sma50": 407.8715,
      "sma150": 422.6277,
      "slope_sma150": -0.7771,
      "ema9": 375.9673,
      "macd": -11.597,
      "macd_signal": -11.1119,
      "macd_histogram": -0.4851,
      "atr": 13.5143,
      "volume_10week_ma": 41248606.0,
      "stage_classification": "Stage 4 (Declining)",
      "confirms_stage2_volume": "N/A",
      "action_signal": "SELL",
      "stage_analysis_summary": "SELL",
      "position": "SELL",
      "signals": [
        "Bearish",
        "MACD Bearish"
      ],
      "signal_type": "bearish"
    },
    {
      "symbol": "QCOM",
      "name": "QUALCOMM Incorporated",
      "date": "2026-07-01",
      "price": 181.92,
      "change": -2.87,
      "change_pct": -1.55,
      "volume": 23283100,
      "avg_volume": 22533195,
      "volume_ratio": 1.0333,
      "rsi": 40.0956,
      "sma20": 209.1895,
      "sma50": 201.2155,
      "sma150": 166.9152,
      "slope_sma150": 0.2539,
      "ema9": 195.6557,
      "macd": -5.239,
      "macd_signal": -0.1927,
      "macd_histogram": -5.0462,
      "atr": 15.345,
      "volume_10week_ma": 26051424.0,
      "stage_classification": "Stage 2 (Advancing)",
      "confirms_stage2_volume": "N/A",
      "action_signal": "HOLD",
      "stage_analysis_summary": "HOLD",
      "position": "HOLD",
      "signals": [
        "MACD Bearish"
      ],
      "signal_type": "bearish"
    },
    {
      "symbol": "GS",
      "name": "Goldman Sachs Group, Inc. (The)",
      "date": "2026-07-01",
      "price": 1019.61,
      "change": 8.24,
      "change_pct": 0.81,
      "volume": 1733200,
      "avg_volume": 2505115,
      "volume_ratio": 0.6919,
      "rsi": 46.6761,
      "sma20": 1056.2575,
      "sma50": 994.2238,
      "sma150": 917.0684,
      "slope_sma150": 1.8459,
      "ema9": 1041.7906,
      "macd": 10.2577,
      "macd_signal": 22.5696,
      "macd_histogram": -12.3119,
      "atr": 31.6457,
      "volume_10week_ma": 2147016.0,
      "stage_classification": "Stage 2 (Advancing)",
      "confirms_stage2_volume": "N/A",
      "action_signal": "HOLD",
      "stage_analysis_summary": "HOLD",
      "position": "HOLD",
      "signals": [
        "MACD Bearish"
      ],
      "signal_type": "bearish"
    },
    {
      "symbol": "TGT",
      "name": "Target Corporation",
      "date": "2026-07-01",
      "price": 130.29,
      "change": -0.32,
      "change_pct": -0.25,
      "volume": 4927800,
      "avg_volume": 4729195,
      "volume_ratio": 1.042,
      "rsi": 49.4265,
      "sma20": 131.1295,
      "sma50": 127.8858,
      "sma150": 114.4222,
      "slope_sma150": 0.2846,
      "ema9": 133.4364,
      "macd": 2.2528,
      "macd_signal": 2.5227,
      "macd_histogram": -0.2699,
      "atr": 4.6343,
      "volume_10week_ma": 5275112.0,
      "stage_classification": "Stage 2 (Advancing)",
      "confirms_stage2_volume": "N/A",
      "action_signal": "HOLD",
      "stage_analysis_summary": "HOLD",
      "position": "HOLD",
      "signals": [
        "MACD Bearish"
      ],
      "signal_type": "bearish"
    },
    {
      "symbol": "PG",
      "name": "Procter & Gamble Company (The)",
      "date": "2026-07-01",
      "price": 147.43,
      "change": 0.79,
      "change_pct": 0.54,
      "volume": 9565400,
      "avg_volume": 9515720,
      "volume_ratio": 1.0052,
      "rsi": 49.7974,
      "sma20": 148.1395,
      "sma50": 145.8898,
      "sma150": 146.8119,
      "slope_sma150": 0.0144,
      "ema9": 148.47,
      "macd": 0.8798,
      "macd_signal": 1.2548,
      "macd_histogram": -0.3749,
      "atr": 2.7857,
      "volume_10week_ma": 9098078.0,
      "stage_classification": "Stage 2 (Advancing)",
      "confirms_stage2_volume": "Strong Volume Confirmation",
      "action_signal": "BUY",
      "stage_analysis_summary": "BUY",
      "position": "BUY",
      "signals": [
        "MACD Bearish"
      ],
      "signal_type": "bearish"
    },
    {
      "symbol": "PEP",
      "name": "Pepsico, Inc.",
      "date": "2026-07-01",
      "price": 141.16,
      "change": 5.76,
      "change_pct": 4.25,
      "volume": 9386000,
      "avg_volume": 9819005,
      "volume_ratio": 0.9559,
      "rsi": 46.7407,
      "sma20": 141.8293,
      "sma50": 146.6222,
      "sma150": 149.5254,
      "slope_sma150": 0.0015,
      "ema9": 140.2868,
      "macd": -1.9585,
      "macd_signal": -1.8437,
      "macd_histogram": -0.1148,
      "atr": 3.2636,
      "volume_10week_ma": 7941706.0,
      "stage_classification": "Transitional",
      "confirms_stage2_volume": "N/A",
      "action_signal": "HOLD",
      "stage_analysis_summary": "HOLD",
      "position": "HOLD",
      "signals": [
        "Bearish",
        "MACD Bearish"
      ],
      "signal_type": "bearish"
    },
    {
      "symbol": "PFE",
      "name": "Pfizer, Inc.",
      "date": "2026-07-01",
      "price": 23.88,
      "change": -0.2,
      "change_pct": -0.83,
      "volume": 49349900,
      "avg_volume": 48035105,
      "volume_ratio": 1.0274,
      "rsi": 32.8592,
      "sma20": 25.1835,
      "sma50": 25.6548,
      "sma150": 25.7712,
      "slope_sma150": 0.0089,
      "ema9": 24.4245,
      "macd": -0.5108,
      "macd_signal": -0.3595,
      "macd_histogram": -0.1513,
      "atr": 0.6129,
      "volume_10week_ma": 41384878.0,
      "stage_classification": "Transitional",
      "confirms_stage2_volume": "N/A",
      "action_signal": "HOLD",
      "stage_analysis_summary": "HOLD",
      "position": "HOLD",
      "signals": [
        "Bearish",
        "MACD Bearish"
      ],
      "signal_type": "bearish"
    },
    {
      "symbol": "DIS",
      "name": "Walt Disney Company (The)",
      "date": "2026-07-01",
      "price": 95.71,
      "change": -0.54,
      "change_pct": -0.56,
      "volume": 11579600,
      "avg_volume": 11196500,
      "volume_ratio": 1.0342,
      "rsi": 37.2244,
      "sma20": 99.2074,
      "sma50": 101.4477,
      "sma150": 103.838,
      "slope_sma150": -0.0601,
      "ema9": 98.1758,
      "macd": -1.1087,
      "macd_signal": -0.6809,
      "macd_histogram": -0.4278,
      "atr": 2.3882,
      "volume_10week_ma": 9735078.0,
      "stage_classification": "Stage 4 (Declining)",
      "confirms_stage2_volume": "N/A",
      "action_signal": "SELL",
      "stage_analysis_summary": "SELL",
      "position": "SELL",
      "signals": [
        "Bearish",
        "MACD Bearish"
      ],
      "signal_type": "bearish"
    },
    {
      "symbol": "BA",
      "name": "Boeing Company (The)",
      "date": "2026-07-01",
      "price": 218.58,
      "change": 2.11,
      "change_pct": 0.97,
      "volume": 4204500,
      "avg_volume": 6324950,
      "volume_ratio": 0.6647,
      "rsi": 48.3717,
      "sma20": 218.5625,
      "sma50": 223.6362,
      "sma150": 221.4091,
      "slope_sma150": 0.1394,
      "ema9": 218.303,
      "macd": -1.2753,
      "macd_signal": -1.0127,
      "macd_histogram": -0.2626,
      "atr": 6.6914,
      "volume_10week_ma": 6763806.0,
      "stage_classification": "Transitional",
      "confirms_stage2_volume": "N/A",
      "action_signal": "HOLD",
      "stage_analysis_summary": "HOLD",
      "position": "HOLD",
      "signals": [
        "MACD Bearish"
      ],
      "signal_type": "bearish"
    },
    {
      "symbol": "RGTI",
      "name": "Rigetti Computing, Inc.",
      "date": "2026-07-01",
      "price": 18.68,
      "change": -0.64,
      "change_pct": -3.31,
      "volume": 24442300,
      "avg_volume": 41070230,
      "volume_ratio": 0.5951,
      "rsi": 43.3932,
      "sma20": 20.6395,
      "sma50": 20.1672,
      "sma150": 20.1001,
      "slope_sma150": -0.0787,
      "ema9": 19.5681,
      "macd": -0.544,
      "macd_signal": -0.1733,
      "macd_histogram": -0.3707,
      "atr": 1.8157,
      "volume_10week_ma": 43405152.0,
      "stage_classification": "Stage 4 (Declining)",
      "confirms_stage2_volume": "N/A",
      "action_signal": "SELL",
      "stage_analysis_summary": "SELL",
      "position": "SELL",
      "signals": [
        "MACD Bearish"
      ],
      "signal_type": "bearish"
    },
    {
      "symbol": "GLD",
      "name": "SPDR Gold Shares",
      "date": "2026-07-01",
      "price": 370.6,
      "change": 2.22,
      "change_pct": 0.6,
      "volume": 9034500,
      "avg_volume": 8359240,
      "volume_ratio": 1.0808,
      "rsi": 35.2385,
      "sma20": 384.9625,
      "sma50": 407.4024,
      "sma150": 424.1737,
      "slope_sma150": 0.0872,
      "ema9": 374.4922,
      "macd": -11.5785,
      "macd_signal": -10.8791,
      "macd_histogram": -0.6994,
      "atr": 8.4464,
      "volume_10week_ma": 7106094.0,
      "stage_classification": "Transitional",
      "confirms_stage2_volume": "N/A",
      "action_signal": "HOLD",
      "stage_analysis_summary": "HOLD",
      "position": "HOLD",
      "signals": [
        "Bearish",
        "MACD Bearish"
      ],
      "signal_type": "bearish"
    },
    {
      "symbol": "SLV",
      "name": "iShares Silver Trust",
      "date": "2026-07-01",
      "price": 53.58,
      "change": 0.11,
      "change_pct": 0.21,
      "volume": 16095100,
      "avg_volume": 23494825,
      "volume_ratio": 0.685,
      "rsi": 33.5369,
      "sma20": 58.6945,
      "sma50": 65.2846,
      "sma150": 68.6175,
      "slope_sma150": 0.0922,
      "ema9": 54.9024,
      "macd": -3.7979,
      "macd_signal": -3.3826,
      "macd_histogram": -0.4153,
      "atr": 2.5379,
      "volume_10week_ma": 22548380.0,
      "stage_classification": "Transitional",
      "confirms_stage2_volume": "N/A",
      "action_signal": "HOLD",
      "stage_analysis_summary": "HOLD",
      "position": "HOLD",
      "signals": [
        "Bearish",
        "MACD Bearish"
      ],
      "signal_type": "bearish"
    },
    {
      "symbol": "PPLT",
      "name": "abrdn Physical Platinum Shares ",
      "date": "2026-07-01",
      "price": 14.29,
      "change": 0.16,
      "change_pct": 1.13,
      "volume": 2880900,
      "avg_volume": 3039560,
      "volume_ratio": 0.9478,
      "rsi": 33.9496,
      "sma20": 15.401,
      "sma50": 16.9873,
      "sma150": 18.3175,
      "slope_sma150": 0.0079,
      "ema9": 14.6758,
      "macd": -0.8155,
      "macd_signal": -0.7533,
      "macd_histogram": -0.0622,
      "atr": 0.5114,
      "volume_10week_ma": 2633854.0,
      "stage_classification": "Transitional",
      "confirms_stage2_volume": "N/A",
      "action_signal": "HOLD",
      "stage_analysis_summary": "HOLD",
      "position": "HOLD",
      "signals": [
        "Bearish",
        "MACD Bearish"
      ],
      "signal_type": "bearish"
    },
    {
      "symbol": "XME",
      "name": "State Street SPDR S&P Metals & ",
      "date": "2026-07-01",
      "price": 104.36,
      "change": -2.57,
      "change_pct": -2.4,
      "volume": 5120400,
      "avg_volume": 2089380,
      "volume_ratio": 2.4507,
      "rsi": 32.8224,
      "sma20": 115.1989,
      "sma50": 118.0249,
      "sma150": 114.1359,
      "slope_sma150": 0.1477,
      "ema9": 109.2173,
      "macd": -3.6916,
      "macd_signal": -2.3118,
      "macd_histogram": -1.3798,
      "atr": 3.6324,
      "volume_10week_ma": 2245706.0,
      "stage_classification": "Transitional",
      "confirms_stage2_volume": "N/A",
      "action_signal": "HOLD",
      "stage_analysis_summary": "HOLD",
      "position": "HOLD",
      "signals": [
        "Bearish",
        "MACD Bearish",
        "High Volume"
      ],
      "signal_type": "bearish"
    },
    {
      "symbol": "COPX",
      "name": "Global X Copper Miners ETF",
      "date": "2026-07-01",
      "price": 75.29,
      "change": -1.68,
      "change_pct": -2.18,
      "volume": 4562600,
      "avg_volume": 3771990,
      "volume_ratio": 1.2096,
      "rsi": 38.7131,
      "sma20": 81.8451,
      "sma50": 82.9971,
      "sma150": 79.9262,
      "slope_sma150": 0.1519,
      "ema9": 78.1149,
      "macd": -2.3053,
      "macd_signal": -1.2876,
      "macd_histogram": -1.0177,
      "atr": 3.2091,
      "volume_10week_ma": 4080432.0,
      "stage_classification": "Transitional",
      "confirms_stage2_volume": "N/A",
      "action_signal": "HOLD",
      "stage_analysis_summary": "HOLD",
      "position": "HOLD",
      "signals": [
        "Bearish",
        "MACD Bearish"
      ],
      "signal_type": "bearish"
    },
    {
      "symbol": "COST",
      "name": "Costco Wholesale Corporation",
      "date": "2026-07-01",
      "price": 924.67,
      "change": -10.8,
      "change_pct": -1.15,
      "volume": 2907600,
      "avg_volume": 2557660,
      "volume_ratio": 1.1368,
      "rsi": 33.4276,
      "sma20": 962.2845,
      "sma50": 993.1688,
      "sma150": 965.6652,
      "slope_sma150": 0.3241,
      "ema9": 946.7097,
      "macd": -16.0297,
      "macd_signal": -13.4871,
      "macd_histogram": -2.5425,
      "atr": 18.365,
      "volume_10week_ma": 2330668.0,
      "stage_classification": "Transitional",
      "confirms_stage2_volume": "N/A",
      "action_signal": "HOLD",
      "stage_analysis_summary": "HOLD",
      "position": "HOLD",
      "signals": [
        "Bearish",
        "MACD Bearish"
      ],
      "signal_type": "bearish"
    },
    {
      "symbol": "NKE",
      "name": "Nike, Inc.",
      "date": "2026-07-01",
      "price": 43.06,
      "change": 2.01,
      "change_pct": 4.9,
      "volume": 80135500,
      "avg_volume": 25752325,
      "volume_ratio": 3.1118,
      "rsi": 48.8487,
      "sma20": 43.37,
      "sma50": 43.6654,
      "sma150": 53.5549,
      "slope_sma150": -0.1252,
      "ema9": 42.2934,
      "macd": -0.7244,
      "macd_signal": -0.5156,
      "macd_histogram": -0.2088,
      "atr": 1.4786,
      "volume_10week_ma": 23890788.0,
      "stage_classification": "Stage 4 (Declining)",
      "confirms_stage2_volume": "N/A",
      "action_signal": "SELL",
      "stage_analysis_summary": "SELL",
      "position": "SELL",
      "signals": [
        "Bearish",
        "MACD Bearish",
        "High Volume"
      ],
      "signal_type": "bearish"
    },
    {
      "symbol": "MCD",
      "name": "McDonald's Corporation",
      "date": "2026-07-01",
      "price": 269.43,
      "change": -0.88,
      "change_pct": -0.33,
      "volume": 3898100,
      "avg_volume": 4821845,
      "volume_ratio": 0.8084,
      "rsi": 41.5828,
      "sma20": 276.566,
      "sma50": 280.0318,
      "sma150": 301.2046,
      "slope_sma150": -0.1435,
      "ema9": 271.5222,
      "macd": -3.5624,
      "macd_signal": -2.7151,
      "macd_histogram": -0.8473,
      "atr": 5.5036,
      "volume_10week_ma": 4427666.0,
      "stage_classification": "Stage 4 (Declining)",
      "confirms_stage2_volume": "N/A",
      "action_signal": "SELL",
      "stage_analysis_summary": "SELL",
      "position": "SELL",
      "signals": [
        "Bearish",
        "MACD Bearish"
      ],
      "signal_type": "bearish"
    },
    {
      "symbol": "PM",
      "name": "Philip Morris International Inc",
      "date": "2026-07-01",
      "price": 177.69,
      "change": -3.22,
      "change_pct": -1.78,
      "volume": 5902800,
      "avg_volume": 5273615,
      "volume_ratio": 1.1193,
      "rsi": 49.3951,
      "sma20": 178.2612,
      "sma50": 175.9614,
      "sma150": 168.2309,
      "slope_sma150": 0.2023,
      "ema9": 179.1884,
      "macd": 0.8385,
      "macd_signal": 0.8677,
      "macd_histogram": -0.0292,
      "atr": 4.8003,
      "volume_10week_ma": 5102486.0,
      "stage_classification": "Stage 2 (Advancing)",
      "confirms_stage2_volume": "Strong Volume Confirmation",
      "action_signal": "BUY",
      "stage_analysis_summary": "BUY",
      "position": "BUY",
      "signals": [
        "MACD Bearish"
      ],
      "signal_type": "bearish"
    },
    {
      "symbol": "NFLX",
      "name": "Netflix, Inc.",
      "date": "2026-07-01",
      "price": 74.19,
      "change": 2.79,
      "change_pct": 3.91,
      "volume": 43725500,
      "avg_volume": 48560695,
      "volume_ratio": 0.9004,
      "rsi": 37.5201,
      "sma20": 77.4635,
      "sma50": 84.4178,
      "sma150": 89.7587,
      "slope_sma150": -0.221,
      "ema9": 74.0628,
      "macd": -3.7273,
      "macd_signal": -3.6438,
      "macd_histogram": -0.0836,
      "atr": 2.6843,
      "volume_10week_ma": 40162470.0,
      "stage_classification": "Stage 4 (Declining)",
      "confirms_stage2_volume": "N/A",
      "action_signal": "SELL",
      "stage_analysis_summary": "SELL",
      "position": "SELL",
      "signals": [
        "Bearish",
        "MACD Bearish"
      ],
      "signal_type": "bearish"
    },
    {
      "symbol": "MDLZ",
      "name": "Mondelez International, Inc.",
      "date": "2026-07-01",
      "price": 59.35,
      "change": 1.51,
      "change_pct": 2.61,
      "volume": 12145200,
      "avg_volume": 9975525,
      "volume_ratio": 1.2175,
      "rsi": 45.1474,
      "sma20": 60.8228,
      "sma50": 60.3875,
      "sma150": 57.5442,
      "slope_sma150": 0.0348,
      "ema9": 59.8238,
      "macd": -0.3645,
      "macd_signal": -0.049,
      "macd_histogram": -0.3155,
      "atr": 1.54,
      "volume_10week_ma": 8719194.0,
      "stage_classification": "Stage 2 (Advancing)",
      "confirms_stage2_volume": "Strong Volume Confirmation",
      "action_signal": "BUY",
      "stage_analysis_summary": "BUY",
      "position": "BUY",
      "signals": [
        "MACD Bearish"
      ],
      "signal_type": "bearish"
    },
    {
      "symbol": "XOM",
      "name": "Exxon Mobil Corporation",
      "date": "2026-07-01",
      "price": 136.28,
      "change": -0.44,
      "change_pct": -0.32,
      "volume": 12418600,
      "avg_volume": 18227865,
      "volume_ratio": 0.6813,
      "rsi": 34.6331,
      "sma20": 142.948,
      "sma50": 147.7575,
      "sma150": 141.4521,
      "slope_sma150": 0.1906,
      "ema9": 138.024,
      "macd": -3.8455,
      "macd_signal": -3.3826,
      "macd_histogram": -0.4629,
      "atr": 3.3464,
      "volume_10week_ma": 17399348.0,
      "stage_classification": "Transitional",
      "confirms_stage2_volume": "N/A",
      "action_signal": "HOLD",
      "stage_analysis_summary": "HOLD",
      "position": "HOLD",
      "signals": [
        "Bearish",
        "MACD Bearish"
      ],
      "signal_type": "bearish"
    },
    {
      "symbol": "VZ",
      "name": "Verizon Communications Inc.",
      "date": "2026-07-01",
      "price": 41.99,
      "change": -0.35,
      "change_pct": -0.83,
      "volume": 57110900,
      "avg_volume": 30036505,
      "volume_ratio": 1.9014,
      "rsi": 30.6131,
      "sma20": 45.6965,
      "sma50": 46.7284,
      "sma150": 44.9965,
      "slope_sma150": 0.0448,
      "ema9": 44.4889,
      "macd": -0.9317,
      "macd_signal": -0.5137,
      "macd_histogram": -0.418,
      "atr": 1.3829,
      "volume_10week_ma": 26088094.0,
      "stage_classification": "Transitional",
      "confirms_stage2_volume": "N/A",
      "action_signal": "HOLD",
      "stage_analysis_summary": "HOLD",
      "position": "HOLD",
      "signals": [
        "Bearish",
        "MACD Bearish"
      ],
      "signal_type": "bearish"
    },
    {
      "symbol": "NOC",
      "name": "Northrop Grumman Corporation",
      "date": "2026-07-01",
      "price": 519.95,
      "change": 10.64,
      "change_pct": 2.09,
      "volume": 902100,
      "avg_volume": 1097640,
      "volume_ratio": 0.8219,
      "rsi": 44.0826,
      "sma20": 528.2945,
      "sma50": 546.8135,
      "sma150": 617.7816,
      "slope_sma150": -0.2455,
      "ema9": 513.2584,
      "macd": -14.5351,
      "macd_signal": -14.1065,
      "macd_histogram": -0.4286,
      "atr": 14.94,
      "volume_10week_ma": 976344.0,
      "stage_classification": "Stage 4 (Declining)",
      "confirms_stage2_volume": "N/A",
      "action_signal": "SELL",
      "stage_analysis_summary": "SELL",
      "position": "SELL",
      "signals": [
        "Bearish",
        "MACD Bearish"
      ],
      "signal_type": "bearish"
    },
    {
      "symbol": "LHX",
      "name": "L3Harris Technologies, Inc.",
      "date": "2026-07-01",
      "price": 292.23,
      "change": 1.64,
      "change_pct": 0.56,
      "volume": 1911100,
      "avg_volume": 1485790,
      "volume_ratio": 1.2863,
      "rsi": 42.8944,
      "sma20": 299.6633,
      "sma50": 306.6956,
      "sma150": 323.0902,
      "slope_sma150": 0.0882,
      "ema9": 292.9806,
      "macd": -5.8464,
      "macd_signal": -5.3054,
      "macd_histogram": -0.541,
      "atr": 9.5343,
      "volume_10week_ma": 1498680.0,
      "stage_classification": "Transitional",
      "confirms_stage2_volume": "N/A",
      "action_signal": "HOLD",
      "stage_analysis_summary": "HOLD",
      "position": "HOLD",
      "signals": [
        "Bearish",
        "MACD Bearish"
      ],
      "signal_type": "bearish"
    },
    {
      "symbol": "UNG",
      "name": "United States Natural Gas Fund ",
      "date": "2026-07-01",
      "price": 11.52,
      "change": -0.2,
      "change_pct": -1.71,
      "volume": 3675200,
      "avg_volume": 5855690,
      "volume_ratio": 0.6276,
      "rsi": 49.8261,
      "sma20": 11.605,
      "sma50": 11.2424,
      "sma150": 12.0771,
      "slope_sma150": -0.0152,
      "ema9": 11.6255,
      "macd": 0.0814,
      "macd_signal": 0.1016,
      "macd_histogram": -0.0202,
      "atr": 0.355,
      "volume_10week_ma": 8260966.0,
      "stage_classification": "Stage 4 (Declining)",
      "confirms_stage2_volume": "N/A",
      "action_signal": "SELL",
      "stage_analysis_summary": "SELL",
      "position": "SELL",
      "signals": [
        "MACD Bearish"
      ],
      "signal_type": "bearish"
    },
    {
      "symbol": "XLE",
      "name": "State Street Energy Select Sect",
      "date": "2026-07-01",
      "price": 52.81,
      "change": -0.3,
      "change_pct": -0.56,
      "volume": 33607600,
      "avg_volume": 34053115,
      "volume_ratio": 0.9869,
      "rsi": 34.9355,
      "sma20": 55.3874,
      "sma50": 56.6913,
      "sma150": 53.0149,
      "slope_sma150": 0.0784,
      "ema9": 53.8137,
      "macd": -1.1288,
      "macd_signal": -0.9226,
      "macd_histogram": -0.2061,
      "atr": 1.1705,
      "volume_10week_ma": 37014458.0,
      "stage_classification": "Transitional",
      "confirms_stage2_volume": "N/A",
      "action_signal": "HOLD",
      "stage_analysis_summary": "HOLD",
      "position": "HOLD",
      "signals": [
        "Bearish",
        "MACD Bearish"
      ],
      "signal_type": "bearish"
    },
    {
      "symbol": "NVDA",
      "name": "NVIDIA Corporation",
      "date": "2026-07-01",
      "price": 197.58,
      "change": -2.51,
      "change_pct": -1.25,
      "volume": 145771900,
      "avg_volume": 160572780,
      "volume_ratio": 0.9078,
      "rsi": 43.3206,
      "sma20": 204.4685,
      "sma50": 209.7429,
      "sma150": 192.2364,
      "slope_sma150": 0.0784,
      "ema9": 199.5058,
      "macd": -3.8508,
      "macd_signal": -2.7831,
      "macd_histogram": -1.0677,
      "atr": 6.2271,
      "volume_10week_ma": 163089204.0,
      "stage_classification": "Stage 2 (Advancing)",
      "confirms_stage2_volume": "N/A",
      "action_signal": "HOLD",
      "stage_analysis_summary": "HOLD",
      "position": "HOLD",
      "signals": [
        "Bearish",
        "MACD Bearish"
      ],
      "signal_type": "bearish"
    },
    {
      "symbol": "TXN",
      "name": "Texas Instruments Incorporated",
      "date": "2026-07-01",
      "price": 298.41,
      "change": 0.34,
      "change_pct": 0.11,
      "volume": 8733800,
      "avg_volume": 10612670,
      "volume_ratio": 0.823,
      "rsi": 49.9149,
      "sma20": 301.076,
      "sma50": 294.3573,
      "sma150": 228.3233,
      "slope_sma150": 0.9508,
      "ema9": 299.6878,
      "macd": 1.5618,
      "macd_signal": 4.1835,
      "macd_histogram": -2.6217,
      "atr": 15.8471,
      "volume_10week_ma": 9540704.0,
      "stage_classification": "Stage 2 (Advancing)",
      "confirms_stage2_volume": "N/A",
      "action_signal": "HOLD",
      "stage_analysis_summary": "HOLD",
      "position": "HOLD",
      "signals": [
        "MACD Bearish"
      ],
      "signal_type": "bearish"
    },
    {
      "symbol": "AVGO",
      "name": "Broadcom Inc.",
      "date": "2026-07-01",
      "price": 369.34,
      "change": -8.41,
      "change_pct": -2.23,
      "volume": 23652000,
      "avg_volume": 37258810,
      "volume_ratio": 0.6348,
      "rsi": 42.0982,
      "sma20": 389.8763,
      "sma50": 409.7105,
      "sma150": 364.8884,
      "slope_sma150": 0.2397,
      "ema9": 378.4053,
      "macd": -10.6502,
      "macd_signal": -8.5305,
      "macd_histogram": -2.1197,
      "atr": 15.5941,
      "volume_10week_ma": 27069952.0,
      "stage_classification": "Stage 2 (Advancing)",
      "confirms_stage2_volume": "N/A",
      "action_signal": "HOLD",
      "stage_analysis_summary": "HOLD",
      "position": "HOLD",
      "signals": [
        "Bearish",
        "MACD Bearish"
      ],
      "signal_type": "bearish"
    },
    {
      "symbol": "IONQ",
      "name": "IonQ, Inc.",
      "date": "2026-07-01",
      "price": 51.4,
      "change": -1.86,
      "change_pct": -3.49,
      "volume": 14389600,
      "avg_volume": 28141765,
      "volume_ratio": 0.5113,
      "rsi": 43.7321,
      "sma20": 56.9645,
      "sma50": 54.8988,
      "sma150": 45.4084,
      "slope_sma150": 0.0237,
      "ema9": 53.6319,
      "macd": -1.2786,
      "macd_signal": -0.183,
      "macd_histogram": -1.0957,
      "atr": 4.5564,
      "volume_10week_ma": 30770026.0,
      "stage_classification": "Stage 2 (Advancing)",
      "confirms_stage2_volume": "N/A",
      "action_signal": "HOLD",
      "stage_analysis_summary": "HOLD",
      "position": "HOLD",
      "signals": [
        "MACD Bearish"
      ],
      "signal_type": "bearish"
    },
    {
      "symbol": "FCX",
      "name": "Freeport-McMoRan, Inc.",
      "date": "2026-07-01",
      "price": 60.53,
      "change": -2.36,
      "change_pct": -3.75,
      "volume": 15523400,
      "avg_volume": 15331510,
      "volume_ratio": 1.0125,
      "rsi": 40.7183,
      "sma20": 65.6225,
      "sma50": 63.7752,
      "sma150": 59.57,
      "slope_sma150": 0.1683,
      "ema9": 63.3242,
      "macd": -0.7113,
      "macd_signal": 0.146,
      "macd_histogram": -0.8573,
      "atr": 2.7586,
      "volume_10week_ma": 14842766.0,
      "stage_classification": "Stage 2 (Advancing)",
      "confirms_stage2_volume": "Strong Volume Confirmation",
      "action_signal": "BUY",
      "stage_analysis_summary": "BUY",
      "position": "BUY",
      "signals": [
        "MACD Bearish"
      ],
      "signal_type": "bearish"
    },
    {
      "symbol": "V",
      "name": "Visa Inc.",
      "date": "2026-07-01",
      "price": 351.08,
      "change": 7.99,
      "change_pct": 2.33,
      "volume": 13021400,
      "avg_volume": 8901820,
      "volume_ratio": 1.4628,
      "rsi": 71.549,
      "sma20": 328.4855,
      "sma50": 324.7285,
      "sma150": 324.1084,
      "slope_sma150": -0.036,
      "ema9": 337.724,
      "macd": 5.4276,
      "macd_signal": 3.1624,
      "macd_histogram": 2.2652,
      "atr": 7.4264,
      "volume_10week_ma": 8475982.0,
      "stage_classification": "Transitional",
      "confirms_stage2_volume": "N/A",
      "action_signal": "HOLD",
      "stage_analysis_summary": "HOLD",
      "position": "HOLD",
      "signals": [
        "Overbought",
        "Bullish",
        "MACD Bullish"
      ],
      "signal_type": "overbought"
    },
    {
      "symbol": "KMB",
      "name": "Kimberly-Clark Corporation",
      "date": "2026-07-01",
      "price": 111.44,
      "change": 1.67,
      "change_pct": 1.52,
      "volume": 4782100,
      "avg_volume": 5198005,
      "volume_ratio": 0.92,
      "rsi": 72.5424,
      "sma20": 103.0303,
      "sma50": 99.0418,
      "sma150": 99.409,
      "slope_sma150": -0.0006,
      "ema9": 107.6527,
      "macd": 3.3249,
      "macd_signal": 2.4714,
      "macd_histogram": 0.8535,
      "atr": 2.385,
      "volume_10week_ma": 4812478.0,
      "stage_classification": "Transitional",
      "confirms_stage2_volume": "N/A",
      "action_signal": "HOLD",
      "stage_analysis_summary": "HOLD",
      "position": "HOLD",
      "signals": [
        "Overbought",
        "Bullish",
        "MACD Bullish"
      ],
      "signal_type": "overbought"
    },
    {
      "symbol": "ABBV",
      "name": "AbbVie Inc.",
      "date": "2026-07-01",
      "price": 251.06,
      "change": -0.58,
      "change_pct": -0.23,
      "volume": 6982800,
      "avg_volume": 8863830,
      "volume_ratio": 0.7878,
      "rsi": 72.3002,
      "sma20": 231.509,
      "sma50": 217.5014,
      "sma150": 218.5472,
      "slope_sma150": 0.0617,
      "ema9": 243.378,
      "macd": 9.4249,
      "macd_signal": 6.8934,
      "macd_histogram": 2.5316,
      "atr": 6.7064,
      "volume_10week_ma": 7305488.0,
      "stage_classification": "Stage 2 (Advancing)",
      "confirms_stage2_volume": "N/A",
      "action_signal": "HOLD",
      "stage_analysis_summary": "HOLD",
      "position": "HOLD",
      "signals": [
        "Overbought",
        "Bullish",
        "MACD Bullish"
      ],
      "signal_type": "overbought"
    }
  ]
}